gradeit/__init__.py
gradeit/coordinate.py
gradeit/filter_bridge.py
gradeit/grade.py
gradeit/gradeit.py
gradeit/py.typed
gradeit/elevation/__init__.py
gradeit/elevation/elevation_model.py
gradeit/elevation/filtering.py
gradeit/elevation/usgs_api.py
gradeit/elevation/usgs_local.py
gradeit-0.1.2.dist-info/LICENSE
gradeit-0.1.2.dist-info/METADATA
gradeit-0.1.2.dist-info/WHEEL
gradeit-0.1.2.dist-info/top_level.txt
gradeit-0.1.2.dist-info/RECORD
