Metadata-Version: 2.1
Name: gradeit
Version: 0.1.2
Summary: Road Grade Inference Tool (GradeIT) appends elevation and road grade to a sequence of GPS points.
Author: National Renewable Energy Laboratory
License: BSD 3-Clause License Copyright (c) 2020, Alliance for Sustainable Energy, LLC
Project-URL: Homepage, https://github.com/NREL/gradeit
Keywords: gps,elevation,road grade
Classifier: Development Status :: 3 - Alpha
Classifier: Intended Audience :: Science/Research
Classifier: License :: Other/Proprietary License
Classifier: Operating System :: OS Independent
Classifier: Programming Language :: Python
Classifier: Programming Language :: Python :: 3.8
Classifier: Topic :: Scientific/Engineering
Requires-Python: >=3.8
License-File: LICENSE
Requires-Dist: numpy
Requires-Dist: pandas
Requires-Dist: requests
Requires-Dist: rasterio
Requires-Dist: scipy
Requires-Dist: tqdm
Requires-Dist: shapely
Provides-Extra: dev
Requires-Dist: black ; extra == 'dev'
Requires-Dist: ruff ; extra == 'dev'
Requires-Dist: mypy ; extra == 'dev'
Requires-Dist: pytest ; extra == 'dev'
Requires-Dist: types-requests ; extra == 'dev'
Provides-Extra: plot
Requires-Dist: matplotlib ; extra == 'plot'
